Metadata-Version: 2.1
Name: bertopic-base-chinese
Version: 0.0.1
Summary: 基于bertopic对中文文档进行主题建模
Home-page: https://pypi.org/user/May.xiaoya.zhang/
Author: may.xiaoya.zhang
Author-email: may.xiaoya.zhang@gmail.com
License: UNKNOWN
Platform: UNKNOWN
